nnpackage/__init__.py
nnpackage/environment.py
nnpackage/atomistic/__init__.py
nnpackage/atomistic/model.py
nnpackage/atomistic/output_modules.py
nnpackage/data/__init__.py
nnpackage/data/atoms.py
nnpackage/data/loader.py
nnpackage/data/merging.py
nnpackage/data/partitioning.py
nnpackage/data/stats.py
nnpackage/nn/__init__.py
nnpackage/nn/acsf.py
nnpackage/nn/activations.py
nnpackage/nn/base.py
nnpackage/nn/blocks.py
nnpackage/nn/cfconv.py
nnpackage/nn/cutoff.py
nnpackage/nn/initializers.py
nnpackage/nn/neighbors.py
nnpackage/representation/__init__.py
nnpackage/representation/hdnn.py
nnpackage/representation/schnet.py
nnpackage/train/__init__.py
nnpackage/train/loss.py
nnpackage/train/metrics.py
nnpackage/train/trainer.py
nnpackage/train/hooks/__init__.py
nnpackage/train/hooks/base_hook.py
nnpackage/train/hooks/logging.py
nnpackage/train/hooks/scheduling.py
nnpackage/utils/__init__.py
nnpackage/utils/basic_utils.py
nnpackage/utils/spectra.py
nnpackage/utils/spk_utils.py
nnpackage-0.0.5.dist-info/LICENSE
nnpackage-0.0.5.dist-info/METADATA
nnpackage-0.0.5.dist-info/WHEEL
nnpackage-0.0.5.dist-info/top_level.txt
nnpackage-0.0.5.dist-info/RECORD
